README.md
setup.py
sum/__init__.py
sum/summing.py
sum_test_test.egg-info/PKG-INFO
sum_test_test.egg-info/SOURCES.txt
sum_test_test.egg-info/dependency_links.txt
sum_test_test.egg-info/top_level.txt