Metadata-Version: 2.1
Name: sum-test-test
Version: 0.2
Summary: A publishing test
Home-page: https://github.com/mohamed-fadl-hanalytics/package_test.git
Author: Test
